{
  "lastName": "TENDULKAR",
  "firstName": "SACHIN",
  "dob": "2025-09-08",
  "nationality": "IND",
  "address": "OLD MUMBAI",
  "passport": "S4859875",
  "cdcNo": "CDC343344",
  "indosNo": "INDO7655",
  "email": "SACHIN@GMAIL.COM",
  "phone": "8996754345",
  "companyName": "SACHIN PVT.LTD",
  "vendorName": "Vendor B",
  "paymentStatus": "CREDIT",
  "rollNo": "10",
  "paymentProof": null,
  "session_id": "",
  "submission_timestamp": "2025-09-19T05:30:27.384Z",
  "ocr_source": "manual_entry",
  "auto_filled": false,
  "timestamp": "20250919_110027",
  "last_updated": "2025-09-19T11:00:27.494423",
  "candidate_folder": "SACHIN_TENDULKAR_S4859875",
  "candidate_folder_path": "C:\\Users\\shank\\OneDrive\\Desktop\\backup_valueadded-main\\backend\\uploads\\images\\SACHIN_TENDULKAR_S4859875",
  "moved_files": []
}